ambisync.py
ambisync-0.2.0.dist-info/LICENSE
ambisync-0.2.0.dist-info/METADATA
ambisync-0.2.0.dist-info/WHEEL
ambisync-0.2.0.dist-info/top_level.txt
ambisync-0.2.0.dist-info/RECORD
