Metadata-Version: 2.1
Name: ambisync
Version: 0.2.0
Summary: Define methods that can dynamically shift between synchronous and async
Home-page: https://github.com/ashafer01/python-ambisync
Author: Alex Shafer
Author-email: ashafer@pm.me
License: MIT
Platform: UNKNOWN
